zorto-0.1.0.dist-info/METADATA
zorto-0.1.0.dist-info/WHEEL
zorto-0.1.0.dist-info/entry_points.txt
zorto/__init__.py
zorto/core.abi3.so
zorto-0.1.0.dist-info/RECORD
