Metadata-Version: 2.4
Name: zorto
Version: 0.1.0
Summary: Zorto, a Zola preprocessor for Python & AI-first websites
Author-email: Cody <cody@dkdc.dev>
Requires-Python: >=3.12
